mozi_cli-1.4.1.dist-info/METADATA
mozi_cli-1.4.1.dist-info/RECORD
mozi_cli-1.4.1.dist-info/WHEEL
mozi_cli-1.4.1.dist-info/entry_points.txt
mozi_cli-1.4.1.dist-info/top_level.txt
mozi_service_cli/__init__.py
mozi_service_cli/mozi_cli.py
