Metadata-Version: 2.1
Name: mozi-cli
Version: 1.4.1
Summary: UNKNOWN
Home-page: https://github.com/Habush/mozi-service-cli
Author: Abdulrahman Semrie
Author-email: hsamireh@gmail.com
License: UNKNOWN
Platform: UNKNOWN
